{
  "model": "scribe_english_v1",
  "language": "en",
  "format": "mp3",
  "sampleRate": 16000,
  "channels": 1,
  "microphonePartId": "4",
  "microphoneDeviceId": "alsa_input.usb-C-Media_Electronics_Inc._USB_Audio_Device-00.mono-fallback",
  "vadEnabled": true,
  "vadThreshold": 0.02,
  "vadSilenceDuration": 500,
  "audioFilterEnabled": false,
  "highpassFreq": 200,
  "lowpassFreq": 4200,
  "denoiseLevel": -20,
  "filterSfx": true,
  "validateEnglish": true,
  "minLetterRatio": 55,
  "requireVowels": true,
  "_preset": "clean-audio",
  "_presetName": "Clean Audio (No Filtering)",
  "_comment": "Switched from webcam mic to USB audio adapter for better quality"
}