[
    {
        "id": "1",
        "name": "Groundbreaker Cam",
        "type": "webcam",
        "pin": null,
        "description": "video capture devices",
        "config": {
            "devicePath": "/dev/video0",
            "deviceId": 0,
            "width": 640,
            "height": 480,
            "fps": 30
        },
        "created": "2025-09-28T02:48:01.673Z",
        "enabled": true
    },
    {
        "id": "2",
        "name": "Groundbreaker Sound System",
        "type": "speaker",
        "pin": null,
        "description": "audio output devices",
        "config": {
            "audioDeviceId": "default",
            "volume": 100,
            "bass": 5,
            "treble": 0
        },
        "created": "2025-09-28T17:47:44.063Z",
        "enabled": true,
        "modelId": "default_speaker"
    },
    {
        "id": "3",
        "name": "Groundbreaker Microphone",
        "type": "microphone",
        "pin": null,
        "description": "audio input devices",
        "config": {
            "deviceId": "default"
        },
        "created": "2025-09-28T17:48:00.000Z",
        "enabled": true
    },
    {
        "id": "52",
        "name": "Wiper Motor Stepper",
        "type": "stepper",
        "pin": null,
        "description": "MDD10A Control Board - Stepper motor for jaw/head movement (Board pins 11,13,15 = GPIO 17,27,22)",
        "config": {
            "controlBoard": "MDD10A",
            "motorType": "stepper",
            "boardPins": {
                "11": "EN (Brown wire)",
                "13": "DIR (Red wire)",
                "15": "STEP (Orange wire)"
            },
            "motorWiring": {
                "blue": "1A",
                "red": "1B",
                "green": "2A",
                "black": "2B"
            },
            "notes": "Jeep Wagoneer wiper motor configured as stepper. Can jumper EN to GND on driver to keep always enabled. Amazon B00WSN98DC (Cytron MDD10A Motor Driver)"
        },
        "created": "2025-10-04T18:00:00.000Z",
        "enabled": true,
        "enablePin": 17,
        "dirPin": 27,
        "stepPin": 22
    }
]