[
  {
    "id": "2",
    "name": "Left Arm of Orlok",
    "type": "linear_actuator",
    "pin": null,
    "description": "extending/retracting movements",
    "config": {
      "modelId": "1757818992065"
    },
    "created": "2025-09-14T17:43:28.627Z",
    "enabled": true,
    "directionPin": 18,
    "pwmPin": 13,
    "maxExtension": 15000,
    "maxRetraction": 15000,
    "updated": "2025-09-14T18:21:37.377Z"
  },
  {
    "id": "3",
    "name": "Right Arm of Orlok",
    "type": "linear_actuator",
    "pin": null,
    "description": "extending/retracting movements",
    "config": {
      "modelId": "1757818992065"
    },
    "created": "2025-09-14T18:22:12.759Z",
    "enabled": true,
    "directionPin": 23,
    "pwmPin": 12,
    "maxExtension": 15000,
    "maxRetraction": 15000
  },
  {
    "id": "4",
    "name": "Head on a Swivel",
    "type": "servo",
    "pin": null,
    "description": "Type: Servo Servo Type: choose “feedback” (for angles) or “continuous” (for rotation) Controller Type: PCA9685 PCA9685: Address=0x40, Frequency=50, Channel=0 (click Ch 0) Model: GoBilda 2000 Series Dual‑Mode (New Spec) Description: optional Pin: leave empty",
    "config": {
      "modelId": "3",
      "servoType": "continuous",
      "controllerType": "pca9685",
      "channel": 0,
      "address": 64,
      "pca9685Frequency": 50,
      "invertDirection": true
    },
    "created": "2025-09-14T22:48:54.499Z",
    "enabled": true,
    "updated": "2025-09-17T00:41:09.524Z"
  },
  {
    "id": "5",
    "name": "Elbow of Orlok",
    "type": "servo",
    "pin": 18,
    "description": "precise angle control: standard, continuous, feedback",
    "config": {
      "modelId": "2",
      "servoType": "standard",
      "controllerType": "pca9685",
      "channel": 4,
      "address": 64,
      "pca9685Frequency": 50
    },
    "created": "2025-09-14T23:11:04.444Z",
    "enabled": true
  },
  {
    "id": "6",
    "name": "Forearm of Orlok",
    "type": "servo",
    "pin": 18,
    "description": "precise angle control: standard, continuous, feedback",
    "config": {
      "servoType": "standard",
      "controllerType": "pca9685",
      "channel": 5,
      "address": 64,
      "pca9685Frequency": 50
    },
    "created": "2025-09-14T23:11:56.004Z",
    "enabled": true
  },
  {
    "id": "7",
    "name": "Eye of Orlok",
    "type": "webcam",
    "pin": null,
    "description": "video capture devices",
    "config": {
      "devicePath": "/dev/video0",
      "deviceId": 0
    },
    "created": "2025-09-17T00:12:54.524Z",
    "enabled": true,
    "updated": "2025-09-17T00:15:40.639Z"
  },
  {
    "id": "8",
    "name": "Orlok Speaker",
    "type": "speaker",
    "pin": null,
    "description": "audio output devices",
    "config": {
      "audioDeviceId": "plughw:CARD=Device,DEV=0",
      "volume": 50,
      "bass": 0,
      "treble": 0
    },
    "created": "2025-09-17T03:38:40.191Z",
    "enabled": true
  },
  {
    "id": "9",
    "name": "asd",
    "type": "microphone",
    "pin": null,
    "description": "audio input devices",
    "config": {
      "deviceId": "sysdefault",
      "sensitivity": 2.5,
      "windowMs": 100,
      "inputGainPercent": 187
    },
    "created": "2025-09-18T02:13:35.224Z",
    "enabled": true,
    "updated": "2025-09-22T01:50:29.385Z"
  },
  {
    "id": "10",
    "name": "Neck",
    "type": "servo",
    "pin": null,
    "description": "Coffin neck servo - standard positioning servo",
    "config": {
      "modelId": "4",
      "servoType": "standard",
      "controllerType": "pca9685",
      "channel": 0,
      "address": 64,
      "pca9685Frequency": 50
    },
    "created": "2025-09-19T20:00:00.000Z",
    "enabled": true
  },
  {
    "id": "11",
    "name": "Jaw Servo",
    "type": "servo",
    "pin": null,
    "description": "Coffin jaw servo - standard positioning servo",
    "config": {
      "modelId": "4",
      "servoType": "standard",
      "controllerType": "pca9685",
      "channel": 4,
      "address": 64,
      "pca9685Frequency": 50
    },
    "created": "2025-09-19T20:00:00.000Z",
    "enabled": true
  },
  {
    "id": "12",
    "name": "Eyes",
    "type": "servo",
    "pin": null,
    "description": "Coffin eyes servo - standard positioning servo",
    "config": {
      "modelId": "4",
      "servoType": "standard",
      "controllerType": "pca9685",
      "channel": 8,
      "address": 64,
      "pca9685Frequency": 50
    },
    "created": "2025-09-19T20:00:00.000Z",
    "enabled": true
  }
]