{
  "jawAnimation": {
    "enabled": true,
    "servoPartId": "10",
    "activeConfigId": "config-1",
    "configs": [
      {
        "id": "config-1",
        "name": "Default",
        "sensitivity": 1,
        "smoothing": 0.6,
        "volumeThreshold": 0.02,
        "attackTime": 50,
        "releaseTime": 150,
        "useBandpassFilter": true,
        "useAGC": true,
        "quantizationLevels": 10,
        "preset": "speech",
        "minAngle": 63,
        "maxAngle": 131,
        "audioLeadTimeMs": 300,
        "testText": "cats and dogs for emmy"
      },
      {
        "id": "config-mmi64pqx4ujm",
        "name": "new",
        "sensitivity": 1,
        "smoothing": 0.6,
        "volumeThreshold": 0.02,
        "attackTime": 50,
        "releaseTime": 150,
        "useBandpassFilter": true,
        "useAGC": true,
        "quantizationLevels": 10,
        "preset": "speech",
        "minAngle": 63,
        "maxAngle": 131,
        "audioLeadTimeMs": 0
      },
      {
        "id": "config-mnalu7mwt6e6",
        "name": "Working March28",
        "sensitivity": 1,
        "smoothing": 0.6,
        "volumeThreshold": 0.02,
        "attackTime": 50,
        "releaseTime": 150,
        "useBandpassFilter": true,
        "useAGC": true,
        "quantizationLevels": 10,
        "preset": "speech",
        "minAngle": 63,
        "maxAngle": 131,
        "audioLeadTimeMs": 300,
        "testText": "cats and dogs for emmy"
      }
    ]
  },
  "headTracking": {
    "opencvEnabled": true,
    "enabled": true,
    "panServoId": "15",
    "webcamPartId": "9",
    "centerDeg": 99,
    "rangeDeg": 160,
    "invertPan": false,
    "smoothing": 0.65,
    "deadzone": 5,
    "motionThreshold": 44,
    "minContourArea": 3000,
    "maxContourArea": 100000,
    "backgroundLearningRate": 0.013,
    "noiseReductionKernelSize": 5,
    "blurSize": 7,
    "dilateSize": 11,
    "varThreshold": 20,
    "targetLockStrength": 9,
    "confirmFrames": 4,
    "detectInterval": 5,
    "detectionMode": "person"
  }
}